Workbook

Sheet customers
A1: Customer_ID | B1: Customer_Name | C1: Gender | D1: Age | E1: City | F1: State | G1: Occupation | H1: Annual_Income | I1: Credit_Limit | J1: Card_Type | K1: Join_Date
A2: C100001 | B2: Sanjay Reddy | C2: Male | D2: 22 | E2: Kochi | F2: Kerala | G2: Banker | H2: 1236213 | I2: 98289 | J2: Silver | K2: 44250
A3: C100002 | B3: Sanjay Verma | C3: Male | D3: 22 | E3: Bengaluru | F3: Karnataka | G3: Teacher | H3: 2419613 | I3: 83478 | J3: Silver | K3: 44645
A4: C100003 | B4: Rohan Nair | C4: Female | D4: 58 | E4: Pune | F4: Maharashtra | G4: Doctor | H4: 327257 | I4: 300926 | J4: Gold | K4: 45562
A5: C100004 | B5: Sneha Das | C5: Male | D5: 69 | E5: Delhi | F5: Delhi | G5: Student | H5: 1893530 | I5: 92676 | J5: Silver | K5: 45301
A6: C100005 | B6: Ishaan Rao | C6: Male | D6: 67 | E6: Ahmedabad | F6: Gujarat | G6: Teacher | H6: 1887688 | I6: 290328 | J6: Gold | K6: 45031
A7: C100006 | B7: Sai Verma | C7: Male | D7: 23 | E7: Vijayawada | F7: Andhra Pradesh | G7: Student | H7: 1513781 | I7: 90458 | J7: Silver | K7: 44784
A8: C100007 | B8: Kiran Joshi | C8: Female | D8: 61 | E8: Indore | F8: Madhya Pradesh | G8: Engineer | H8: 1852651 | I8: 126566 | J8: Silver | K8: 44689
A9: C100008 | B9: Sanjay Gupta | C9: Male | D9: 55 | E9: Kochi | F9: Kerala | G9: Business | H9: 2238859 | I9: 129735 | J9: Silver | K9: 44936
A10: C100009 | B10: Aditya Gupta | C10: Male | D10: 35 | E10: Indore | F10: Madhya Pradesh | G10: Business | H10: 1623105 | I10: 132581 | J10: Silver | K10: 44927
A11: C100010 | B11: Kiran Patel | C11: Male | D11: 62 | E11: Ahmedabad | F11: Gujarat | G11: Teacher | H11: 2996316 | I11: 140142 | J11: Silver | K11: 44416
A12: C100011 | B12: Rahul Patel | C12: Female | D12: 68 | E12: Visakhapatnam | F12: Andhra Pradesh | G12: Consultant | H12: 2747514 | I12: 132350 | J12: Silver | K12: 45313
A13: C100012 | B13: Ishaan Reddy | C13: Male | D13: 69 | E13: Hyderabad | F13: Telangana | G13: Banker | H13: 941062 | I13: 800969 | J13: Platinum | K13: 45560
... A3002: C103001 | B3002: Nisha Reddy | C3002: Female | D3002: 66 | E3002: Ahmedabad | F3002: Gujarat | G3002: Banker | H3002: 1023222 | I3002: 129334 | J3002: Silver | K3002: 45063

Sheet transactions
A1: Transaction_ID | B1: Customer_ID | C1: Transaction_Date | D1: Merchant_Name | E1: Merchant_Category | F1: Amount | G1: Payment_Mode | H1: Reward_Points | I1: Transaction_Status | J1: Fraud_Flag | K1: Outstanding_Balance | L1: Card_Type
A2: T200001 | B2: C100156 | C2: 45345 | D2: MedPlus | E2: Pharmacy | F2: 9487 | G2: Online | H2: 94 | I2: Success | J2: No | K2: 586455 | L2: =_xlfn.XLOOKUP(B2, customers!A:A, customers!J:J) -> Platinum
A3: T200002 | B3: C100191 | C3: 45373 | D3: HP | E3: Fuel | F3: 3716 | G3: Chip | H3: 37 | I3: Success | J3: No | K3: 2848 | L3: =_xlfn.XLOOKUP(B3, customers!A:A, customers!J:J) -> Silver
A4: T200003 | B4: C101151 | C4: 45956 | D4: IRCTC | E4: Travel | F4: 78885 | G4: Chip | H4: 788 | I4: Success | J4: No | K4: 320020 | L4: =_xlfn.XLOOKUP(B4, customers!A:A, customers!J:J) -> Gold
A5: T200004 | B5: C102260 | C5: 45762 | D5: MedPlus | E5: Pharmacy | F5: 2515 | G5: Tap | H5: 25 | I5: Success | J5: No | K5: 128378 | L5: =_xlfn.XLOOKUP(B5, customers!A:A, customers!J:J) -> Silver
A6: T200005 | B6: C100038 | C6: 45442 | D6: Dominos | E6: Dining | F6: 899 | G6: Swipe | H6: 8 | I6: Success | J6: No | K6: 435110 | L6: =_xlfn.XLOOKUP(B6, customers!A:A, customers!J:J) -> Platinum
A7: T200006 | B7: C102530 | C7: 45935 | D7: HP | E7: Fuel | F7: 3632 | G7: Tap | H7: 36 | I7: Success | J7: No | K7: 110774 | L7: =_xlfn.XLOOKUP(B7, customers!A:A, customers!J:J) -> Gold
A8: T200007 | B8: C100445 | C8: 45492 | D8: Vijay Sales | E8: Electronics | F8: 32160 | G8: Chip | H8: 321 | I8: Success | J8: No | K8: 78925 | L8: =_xlfn.XLOOKUP(B8, customers!A:A, customers!J:J) -> Gold
A9: T200008 | B9: C100887 | C9: 45751 | D9: Vijay Sales | E9: Electronics | F9: 11736 | G9: Chip | H9: 117 | I9: Success | J9: No | K9: 25069 | L9: =_xlfn.XLOOKUP(B9, customers!A:A, customers!J:J) -> Gold
A10: T200009 | B10: C101912 | C10: 45730 | D10: Reliance Fresh | E10: Grocery | F10: 5039 | G10: Chip | H10: 50 | I10: Success | J10: No | K10: 483971 | L10: =_xlfn.XLOOKUP(B10, customers!A:A, customers!J:J) -> Platinum
A11: T200010 | B11: C100325 | C11: 45612 | D11: KFC | E11: Dining | F11: 6459 | G11: Swipe | H11: 64 | I11: Success | J11: No | K11: 564325 | L11: =_xlfn.XLOOKUP(B11, customers!A:A, customers!J:J) -> Platinum
A12: T200011 | B12: C100172 | C12: 45675 | D12: Flipkart | E12: Shopping | F12: 8224 | G12: Tap | H12: 82 | I12: Success | J12: No | K12: 101368 | L12: =_xlfn.XLOOKUP(B12, customers!A:A, customers!J:J) -> Silver
A13: T200012 | B13: C100024 | C13: 45893 | D13: IndianOil | E13: Fuel | F13: 4773 | G13: Tap | H13: 47 | I13: Success | J13: No | K13: 18132 | L13: =_xlfn.XLOOKUP(B13, customers!A:A, customers!J:J) -> Silver
... A5001: T205000 | B5001: C101511 | C5001: 45599 | D5001: DMart | E5001: Grocery | F5001: 1893 | G5001: Tap | H5001: 18 | I5001: Success | J5001: No | K5001: 10642 | L5001: =_xlfn.XLOOKUP(B5001, customers!A:A, customers!J:J) -> Silver

Sheet pivot_tables
C7: Total Spending by Card Type
C9: Card_Type | D9: Sum of Amount
C10: Gold | D10: 16229413
C11: Platinum | D11: 6591417
C12: Silver | D12: 24764788
C13: (blank)
C14: Grand Total | D14: 47585618
C17: Spending by Merchant
C19: Merchant_Name | D19: Sum of Amount
C20: Amazon | D20: 1547442
C21: Apollo | D21: 1336306
C22: Coursera | D22: 1063671
C23: Croma | D23: 7563577
C24: DMart | D24: 2152383
C25: Dominos | D25: 1272496
C26: Electricity | D26: 1592372
C27: Flipkart | D27: 1666760
C28: HP | D28: 1921841
C29: IndianOil | D29: 2000987
C30: IRCTC | D30: 5342624
C31: KFC | D31: 1279999
... C38: Grand Total | D38: 47585618
C42: Spending by Payment Mode
C44: Payment_Mode | D44: Sum of Amount
C45: Chip | D45: 12071105
C46: Online | D46: 11496537
C47: Swipe | D47: 11956371
C48: Tap | D48: 12061605
C49: Grand Total | D49: 47585618
